dj_config/__init__.py
dj_config/__version__.py
dj_config/core.py
dj_config-0.0.1.dist-info/LICENSE
dj_config-0.0.1.dist-info/METADATA
dj_config-0.0.1.dist-info/WHEEL
dj_config-0.0.1.dist-info/top_level.txt
dj_config-0.0.1.dist-info/RECORD
