Metadata-Version: 2.1
Name: dj_config
Version: 0.0.1
Summary: This is a fork of the Django library for Heroku apps.
Home-page: https://github.com/ochui/dj_config
Author: Ochui Princewill
Author-email: ochui.princewill@gmail.com
License: MIT
Classifier: License :: OSI Approved :: MIT License
Classifier: Programming Language :: Python
Classifier: Programming Language :: Python :: 2.6
Classifier: Programming Language :: Python :: 2.7
Classifier: Programming Language :: Python :: 3
Classifier: Programming Language :: Python :: 3.3
Classifier: Programming Language :: Python :: 3.4
Classifier: Programming Language :: Python :: 3.5
Classifier: Programming Language :: Python :: 3.6
Classifier: Programming Language :: Python :: Implementation :: CPython
Classifier: Programming Language :: Python :: Implementation :: PyPy
License-File: LICENSE
Requires-Dist: dj-database-url>=0.5.0
Requires-Dist: whitenoise
Requires-Dist: psycopg2
Requires-Dist: django
Requires-Dist: python-dotenv
